Metadata-Version: 1.0
Name: dnsq-probability
Version: 0.1
Summary: Gaussian and Binomial distributions
Home-page: UNKNOWN
Author: Nikolas Souza de Queiroz
Author-email: nikolasdequeiroz@gmail.com
License: UNKNOWN
Platform: UNKNOWN
